{
  "run_id": "run_a2c9e38880fb",
  "written_at": 1773425029.748203,
  "status": "partial",
  "text_summary": "İşlem tamamlandı: /tmp/learned.png\nNot: görsel çıktı doğrulanamadı: /tmp/learned.png",
  "errors": [
    "capability:ui_state_present; capability:active_window_identified"
  ],
  "artifact_manifest": [],
  "metadata": {
    "manifest_path": "/Users/emrekoca/Desktop/bot/.elyan/proofs/run_a2c9e38880fb/manifest.json",
    "action": "take_screenshot",
    "job_type": "system_automation"
  }
}